{"trial_id": "15", "hyperparameters": {"space": [{"class_name": "Int", "config": {"name": "units1", "default": null, "conditions": [], "min_value": 64, "max_value": 1024, "step": 64, "sampling": "linear"}}, {"class_name": "Int", "config": {"name": "units2", "default": null, "conditions": [], "min_value": 16, "max_value": 512, "step": 16, "sampling": "linear"}}, {"class_name": "Float", "config": {"name": "dropout", "default": 0.1, "conditions": [], "min_value": 0.1, "max_value": 0.5, "step": 0.1, "sampling": "linear"}}, {"class_name": "Choice", "config": {"name": "reg_type", "default": "l1", "conditions": [], "values": ["l1", "l2", "l1l2"], "ordered": false}}, {"class_name": "Float", "config": {"name": "reg_factor", "default": 1e-05, "conditions": [], "min_value": 1e-05, "max_value": 0.001, "step": null, "sampling": "log"}}, {"class_name": "Choice", "config": {"name": "learning_rate", "default": 0.001, "conditions": [], "values": [0.001, 0.0005, 0.0001], "ordered": true}}, {"class_name": "Choice", "config": {"name": "activation", "default": "leaky_relu", "conditions": [], "values": ["leaky_relu", "relu", "swish", "tanh"], "ordered": false}}, {"class_name": "Boolean", "config": {"name": "batch_norm", "default": false, "conditions": []}}], "values": {"units1": 448, "units2": 464, "dropout": 0.4, "reg_type": "l2", "reg_factor": 0.00012661534807511304, "learning_rate": 0.001, "activation": "leaky_relu", "batch_norm": true}}, "metrics": {"metrics": {"loss": {"direction": "min", "observations": [{"value": [0.02242768555879593], "step": 19}]}, "mae": {"direction": "min", "observations": [{"value": [0.10844558477401733], "step": 19}]}, "mse": {"direction": "min", "observations": [{"value": [0.018903125077486038], "step": 19}]}, "r2_score": {"direction": "min", "observations": [{"value": [0.9587651491165161], "step": 19}]}, "val_loss": {"direction": "min", "observations": [{"value": [0.01963232085108757], "step": 19}]}, "val_mae": {"direction": "min", "observations": [{"value": [0.1071152463555336], "step": 19}]}, "val_mse": {"direction": "min", "observations": [{"value": [0.01508786715567112], "step": 19}]}, "val_r2_score": {"direction": "min", "observations": [{"value": [0.9674034118652344], "step": 19}]}, "learning_rate": {"direction": "min", "observations": [{"value": [0.0010000000474974513], "step": 19}]}}}, "score": 0.01963232085108757, "best_step": 19, "status": "COMPLETED", "message": null}