{"trial_id": "43", "hyperparameters": {"space": [{"class_name": "Int", "config": {"name": "units1", "default": null, "conditions": [], "min_value": 64, "max_value": 1024, "step": 64, "sampling": "linear"}}, {"class_name": "Int", "config": {"name": "units2", "default": null, "conditions": [], "min_value": 16, "max_value": 512, "step": 16, "sampling": "linear"}}, {"class_name": "Float", "config": {"name": "dropout", "default": 0.1, "conditions": [], "min_value": 0.1, "max_value": 0.5, "step": 0.1, "sampling": "linear"}}, {"class_name": "Choice", "config": {"name": "reg_type", "default": "l1", "conditions": [], "values": ["l1", "l2", "l1l2"], "ordered": false}}, {"class_name": "Float", "config": {"name": "reg_factor", "default": 1e-05, "conditions": [], "min_value": 1e-05, "max_value": 0.001, "step": null, "sampling": "log"}}, {"class_name": "Choice", "config": {"name": "learning_rate", "default": 0.001, "conditions": [], "values": [0.001, 0.0005, 0.0001], "ordered": true}}, {"class_name": "Choice", "config": {"name": "activation", "default": "leaky_relu", "conditions": [], "values": ["leaky_relu", "relu", "swish", "tanh"], "ordered": false}}, {"class_name": "Boolean", "config": {"name": "batch_norm", "default": false, "conditions": []}}], "values": {"units1": 576, "units2": 368, "dropout": 0.4, "reg_type": "l2", "reg_factor": 0.0006618130600395817, "learning_rate": 0.001, "activation": "leaky_relu", "batch_norm": false}}, "metrics": {"metrics": {"loss": {"direction": "min", "observations": [{"value": [0.005062447395175695], "step": 127}]}, "mae": {"direction": "min", "observations": [{"value": [0.05149318277835846], "step": 127}]}, "mse": {"direction": "min", "observations": [{"value": [0.0049695284105837345], "step": 127}]}, "r2_score": {"direction": "min", "observations": [{"value": [0.9891595840454102], "step": 127}]}, "val_loss": {"direction": "min", "observations": [{"value": [0.003941481467336416], "step": 127}]}, "val_mae": {"direction": "min", "observations": [{"value": [0.03409045562148094], "step": 127}]}, "val_mse": {"direction": "min", "observations": [{"value": [0.0027272228617221117], "step": 127}]}, "val_r2_score": {"direction": "min", "observations": [{"value": [0.9941079616546631], "step": 127}]}, "learning_rate": {"direction": "min", "observations": [{"value": [9.999999974752427e-07], "step": 127}]}}}, "score": 0.003941481467336416, "best_step": 127, "status": "COMPLETED", "message": null}